pyxccd-1.0.2.dist-info/RECORD
pyxccd-1.0.2.dist-info/WHEEL
pyxccd-1.0.2.dist-info/top_level.txt
pyxccd-1.0.2.dist-info/METADATA
pyxccd-1.0.2.dist-info/licenses/LICENSE
pyxccd-1.0.2.data/data/build_wheels.sh
pyxccd-1.0.2.data/data/CMakeLists.txt
pyxccd-1.0.2.data/data/LICENSE
pyxccd-1.0.2.data/data/requirements.txt
pyxccd-1.0.2.data/data/run_tests.py
pyxccd-1.0.2.data/data/CHANGELOG.md
pyxccd-1.0.2.data/data/pyproject.toml
pyxccd-1.0.2.data/data/.readthedocs.yml
pyxccd-1.0.2.data/data/run_linter.sh
pyxccd-1.0.2.data/data/setup.py
pyxccd-1.0.2.data/data/.gitignore
pyxccd-1.0.2.data/data/run_doctests.sh
pyxccd-1.0.2.data/data/.gitattributes
pyxccd-1.0.2.data/data/clean.sh
pyxccd-1.0.2.data/data/run_developer_setup.sh
pyxccd-1.0.2.data/data/.gitlab-ci.yml
pyxccd-1.0.2.data/data/README.rst
pyxccd-1.0.2.data/data/tests/test_pyclassifier.py
pyxccd-1.0.2.data/data/tests/__init__.py
pyxccd-1.0.2.data/data/tests/test_import.py
pyxccd-1.0.2.data/data/tests/test_sccd.py
pyxccd-1.0.2.data/data/tests/test_pycold.py
pyxccd-1.0.2.data/data/tests/resources/record_change_x2_y1_cold.npy
pyxccd-1.0.2.data/data/tests/resources/LCMAP_CU_2001_V01_LCPRI_027009_100_100.tif
pyxccd-1.0.2.data/data/tests/resources/test_config_obanalyst.yaml
pyxccd-1.0.2.data/data/tests/resources/spectral_336_3980_obs.csv
pyxccd-1.0.2.data/data/tests/resources/record_change_x1_y1_cold.npy
pyxccd-1.0.2.data/data/tests/resources/spectral_336_3980_breaks.csv
pyxccd-1.0.2.data/data/tests/resources/spectral_15043028_sccdplot.pickle
pyxccd-1.0.2.data/data/tests/resources/record_change_x2_y2_cold.npy
pyxccd-1.0.2.data/data/tests/resources/record_change_x1_y2_cold.npy
pyxccd-1.0.2.data/data/tests/resources/record_change_pid15043028_cold.npy
pyxccd-1.0.2.data/data/tests/resources/test_config_pyclassifier.yaml
pyxccd-1.0.2.data/data/tests/resources/spectral_15043028_ext.csv
pyxccd-1.0.2.data/data/tests/resources/cm_maps/CM_maps_730329_2000210.npy
pyxccd-1.0.2.data/data/tests/resources/cm_maps/CM_date_maps_730297_2000178.npy
pyxccd-1.0.2.data/data/tests/resources/cm_maps/CM_date_maps_730663_2000178.npy
