Metadata-Version: 2.4
Name: pyxccd
Version: 1.0.2
Summary: A PYthon library for latest and eXtended COntinuous Change Detection algorithms
Home-page: https://github.com/Remote-Sensing-of-Land-Resource-Lab/pyxccd
Author: Su Ye
Author-email: remotesensingsuy@gmail.com
License: Apache 2
Classifier: Development Status :: 3 - Alpha
Classifier: Intended Audience :: Developers
Classifier: Topic :: Software Development :: Libraries :: Python Modules
Classifier: Topic :: Utilities
Classifier: License :: OSI Approved :: Apache Software License
Classifier: Programming Language :: Python :: 3.9
Classifier: Programming Language :: Python :: 3.10
Classifier: Programming Language :: Python :: 3.11
Classifier: Programming Language :: Python :: 3.12
Classifier: Programming Language :: Python :: 3.13
Requires-Python: >=3.9
License-File: LICENSE
Requires-Dist: numpy>=2.1.0; python_version >= "3.13" and python_version < "4.0"
Requires-Dist: numpy>=2.0.0; python_version >= "3.11" and python_version < "3.13"
Requires-Dist: numpy>=2.0.0; python_version >= "3.9" and python_version < "3.11"
Requires-Dist: joblib>=1.2.0
Requires-Dist: pyyaml<7,>=6.0.2; python_version >= "3.10" and python_version < "4.0"
Requires-Dist: pyyaml<7,>=6.0.2; python_version >= "3.9" and python_version < "3.10"
Requires-Dist: fiona>=1.10.1; python_version >= "3.11" and python_version < "4.0"
Requires-Dist: fiona>=1.10.1; python_version >= "3.9" and python_version < "3.11"
Requires-Dist: scikit-learn>=1.6.0; python_version >= "3.13" and python_version < "4.0"
Requires-Dist: scikit-learn>=1.5.0; python_version >= "3.12" and python_version < "3.13"
Requires-Dist: scikit-learn>=1.5.0; python_version >= "3.11" and python_version < "3.12"
Requires-Dist: scikit-learn>=1.5.0; python_version >= "3.10" and python_version < "3.11"
Requires-Dist: scikit-learn>=1.5.0; python_version >= "3.9" and python_version < "3.10"
Requires-Dist: scikit-image>=0.24.0; python_version >= "3.12" and python_version < "4.0"
Requires-Dist: scikit-image>=0.20.0; python_version >= "3.11" and python_version < "3.12"
Requires-Dist: scikit-image>=0.19.3; python_version >= "3.10" and python_version < "3.11"
Requires-Dist: scikit-image>=0.18.1; python_version >= "3.9" and python_version < "3.10"
Requires-Dist: pandas>=2.2.3; python_version >= "3.12" and python_version < "4.0"
Requires-Dist: pandas>=2.2.3; python_version >= "3.11" and python_version < "3.12"
Requires-Dist: pandas<2.3,>=2.2.3; python_version >= "3.9" and python_version < "3.11"
Requires-Dist: rasterio>=1.4; python_version >= "3.9" and python_version < "4.0"
Provides-Extra: all
Requires-Dist: numpy>=2.1.0; (python_version >= "3.13" and python_version < "4.0") and extra == "all"
Requires-Dist: numpy>=2.0.0; (python_version >= "3.11" and python_version < "3.13") and extra == "all"
Requires-Dist: numpy>=2.0.0; (python_version >= "3.9" and python_version < "3.11") and extra == "all"
Requires-Dist: joblib>=1.2.0; extra == "all"
Requires-Dist: pyyaml<7,>=6.0.2; (python_version >= "3.10" and python_version < "4.0") and extra == "all"
Requires-Dist: pyyaml<7,>=6.0.2; (python_version >= "3.9" and python_version < "3.10") and extra == "all"
Requires-Dist: fiona>=1.10.1; (python_version >= "3.11" and python_version < "4.0") and extra == "all"
Requires-Dist: fiona>=1.10.1; (python_version >= "3.9" and python_version < "3.11") and extra == "all"
Requires-Dist: scikit-learn>=1.6.0; (python_version >= "3.13" and python_version < "4.0") and extra == "all"
Requires-Dist: scikit-learn>=1.5.0; (python_version >= "3.12" and python_version < "3.13") and extra == "all"
Requires-Dist: scikit-learn>=1.5.0; (python_version >= "3.11" and python_version < "3.12") and extra == "all"
Requires-Dist: scikit-learn>=1.5.0; (python_version >= "3.10" and python_version < "3.11") and extra == "all"
Requires-Dist: scikit-learn>=1.5.0; (python_version >= "3.9" and python_version < "3.10") and extra == "all"
Requires-Dist: scikit-image>=0.24.0; (python_version >= "3.12" and python_version < "4.0") and extra == "all"
Requires-Dist: scikit-image>=0.20.0; (python_version >= "3.11" and python_version < "3.12") and extra == "all"
Requires-Dist: scikit-image>=0.19.3; (python_version >= "3.10" and python_version < "3.11") and extra == "all"
Requires-Dist: scikit-image>=0.18.1; (python_version >= "3.9" and python_version < "3.10") and extra == "all"
Requires-Dist: pandas>=2.2.3; (python_version >= "3.12" and python_version < "4.0") and extra == "all"
Requires-Dist: pandas>=2.2.3; (python_version >= "3.11" and python_version < "3.12") and extra == "all"
Requires-Dist: pandas<2.3,>=2.2.3; (python_version >= "3.9" and python_version < "3.11") and extra == "all"
Requires-Dist: rasterio>=1.4; (python_version >= "3.9" and python_version < "4.0") and extra == "all"
Requires-Dist: xdoctest>=1.0.2; extra == "all"
Requires-Dist: ubelt>=1.2.1; extra == "all"
Requires-Dist: requests>=2.25.1; extra == "all"
Requires-Dist: setuptools>=76.0; python_version >= "3.12" and extra == "all"
Requires-Dist: pytest>=6.2.5; python_version >= "3.10" and extra == "all"
Requires-Dist: pytest>=6.2.5; (python_version >= "3.7" and python_version < "3.10") and extra == "all"
Requires-Dist: pytest-cov>=3.0.0; python_version >= "3.6" and extra == "all"
Requires-Dist: pytest-timeout>=1.4.2; extra == "all"
Requires-Dist: coverage>=6.1.1; python_version >= "3.10" and extra == "all"
Requires-Dist: coverage>=5.3.1; (python_version >= "3.9" and python_version < "3.10") and extra == "all"
Requires-Dist: coverage>=6.1.1; (python_version >= "3.8" and python_version < "3.9") and extra == "all"
Requires-Dist: coverage>=6.1.1; (python_version >= "3.7" and python_version < "3.8") and extra == "all"
Requires-Dist: coverage>=6.1.1; (python_version >= "3.6" and python_version < "3.7") and extra == "all"
Requires-Dist: matplotlib>=3.3.4; extra == "all"
Requires-Dist: Seaborn>=0.9.0; extra == "all"
Requires-Dist: click>=7.1.1; extra == "all"
Requires-Dist: scikit-build>=0.11.1; extra == "all"
Requires-Dist: cmake>=3.21.2; extra == "all"
Requires-Dist: cython>=0.29.32; extra == "all"
Requires-Dist: setuptools_scm>=8.2.0; extra == "all"
Provides-Extra: tests
Requires-Dist: xdoctest>=1.0.2; extra == "tests"
Requires-Dist: ubelt>=1.2.1; extra == "tests"
Requires-Dist: requests>=2.25.1; extra == "tests"
Requires-Dist: setuptools>=76.0; python_version >= "3.12" and extra == "tests"
Requires-Dist: pytest>=6.2.5; python_version >= "3.10" and extra == "tests"
Requires-Dist: pytest>=6.2.5; (python_version >= "3.7" and python_version < "3.10") and extra == "tests"
Requires-Dist: pytest-cov>=3.0.0; python_version >= "3.6" and extra == "tests"
Requires-Dist: pytest-timeout>=1.4.2; extra == "tests"
Requires-Dist: coverage>=6.1.1; python_version >= "3.10" and extra == "tests"
Requires-Dist: coverage>=5.3.1; (python_version >= "3.9" and python_version < "3.10") and extra == "tests"
Requires-Dist: coverage>=6.1.1; (python_version >= "3.8" and python_version < "3.9") and extra == "tests"
Requires-Dist: coverage>=6.1.1; (python_version >= "3.7" and python_version < "3.8") and extra == "tests"
Requires-Dist: coverage>=6.1.1; (python_version >= "3.6" and python_version < "3.7") and extra == "tests"
Provides-Extra: optional
Requires-Dist: matplotlib>=3.3.4; extra == "optional"
Requires-Dist: Seaborn>=0.9.0; extra == "optional"
Requires-Dist: click>=7.1.1; extra == "optional"
Provides-Extra: headless
Provides-Extra: graphics
Provides-Extra: headless-strict
Provides-Extra: graphics-strict
Provides-Extra: all-strict
Requires-Dist: numpy==2.1.0; (python_version >= "3.13" and python_version < "4.0") and extra == "all-strict"
Requires-Dist: numpy==2.0.0; (python_version >= "3.11" and python_version < "3.13") and extra == "all-strict"
Requires-Dist: numpy==2.0.0; (python_version >= "3.9" and python_version < "3.11") and extra == "all-strict"
Requires-Dist: joblib==1.2.0; extra == "all-strict"
Requires-Dist: pyyaml<7,==6.0.2; (python_version >= "3.10" and python_version < "4.0") and extra == "all-strict"
Requires-Dist: pyyaml<7,==6.0.2; (python_version >= "3.9" and python_version < "3.10") and extra == "all-strict"
Requires-Dist: fiona==1.10.1; (python_version >= "3.11" and python_version < "4.0") and extra == "all-strict"
Requires-Dist: fiona==1.10.1; (python_version >= "3.9" and python_version < "3.11") and extra == "all-strict"
Requires-Dist: scikit-learn==1.6.0; (python_version >= "3.13" and python_version < "4.0") and extra == "all-strict"
Requires-Dist: scikit-learn==1.5.0; (python_version >= "3.12" and python_version < "3.13") and extra == "all-strict"
Requires-Dist: scikit-learn==1.5.0; (python_version >= "3.11" and python_version < "3.12") and extra == "all-strict"
Requires-Dist: scikit-learn==1.5.0; (python_version >= "3.10" and python_version < "3.11") and extra == "all-strict"
Requires-Dist: scikit-learn==1.5.0; (python_version >= "3.9" and python_version < "3.10") and extra == "all-strict"
Requires-Dist: scikit-image==0.24.0; (python_version >= "3.12" and python_version < "4.0") and extra == "all-strict"
Requires-Dist: scikit-image==0.20.0; (python_version >= "3.11" and python_version < "3.12") and extra == "all-strict"
Requires-Dist: scikit-image==0.19.3; (python_version >= "3.10" and python_version < "3.11") and extra == "all-strict"
Requires-Dist: scikit-image==0.18.1; (python_version >= "3.9" and python_version < "3.10") and extra == "all-strict"
Requires-Dist: pandas==2.2.3; (python_version >= "3.12" and python_version < "4.0") and extra == "all-strict"
Requires-Dist: pandas==2.2.3; (python_version >= "3.11" and python_version < "3.12") and extra == "all-strict"
Requires-Dist: pandas<2.3,==2.2.3; (python_version >= "3.9" and python_version < "3.11") and extra == "all-strict"
Requires-Dist: rasterio==1.4; (python_version >= "3.9" and python_version < "4.0") and extra == "all-strict"
Requires-Dist: xdoctest==1.0.2; extra == "all-strict"
Requires-Dist: ubelt==1.2.1; extra == "all-strict"
Requires-Dist: requests==2.25.1; extra == "all-strict"
Requires-Dist: setuptools==76.0; python_version >= "3.12" and extra == "all-strict"
Requires-Dist: pytest==6.2.5; python_version >= "3.10" and extra == "all-strict"
Requires-Dist: pytest==6.2.5; (python_version >= "3.7" and python_version < "3.10") and extra == "all-strict"
Requires-Dist: pytest-cov==3.0.0; python_version >= "3.6" and extra == "all-strict"
Requires-Dist: pytest-timeout==1.4.2; extra == "all-strict"
Requires-Dist: coverage==6.1.1; python_version >= "3.10" and extra == "all-strict"
Requires-Dist: coverage==5.3.1; (python_version >= "3.9" and python_version < "3.10") and extra == "all-strict"
Requires-Dist: coverage==6.1.1; (python_version >= "3.8" and python_version < "3.9") and extra == "all-strict"
Requires-Dist: coverage==6.1.1; (python_version >= "3.7" and python_version < "3.8") and extra == "all-strict"
Requires-Dist: coverage==6.1.1; (python_version >= "3.6" and python_version < "3.7") and extra == "all-strict"
Requires-Dist: matplotlib==3.3.4; extra == "all-strict"
Requires-Dist: Seaborn==0.9.0; extra == "all-strict"
Requires-Dist: click==7.1.1; extra == "all-strict"
Requires-Dist: scikit-build==0.11.1; extra == "all-strict"
Requires-Dist: cmake==3.21.2; extra == "all-strict"
Requires-Dist: cython==0.29.32; extra == "all-strict"
Requires-Dist: setuptools_scm==8.2.0; extra == "all-strict"
Provides-Extra: runtime-strict
Requires-Dist: numpy==2.1.0; (python_version >= "3.13" and python_version < "4.0") and extra == "runtime-strict"
Requires-Dist: numpy==2.0.0; (python_version >= "3.11" and python_version < "3.13") and extra == "runtime-strict"
Requires-Dist: numpy==2.0.0; (python_version >= "3.9" and python_version < "3.11") and extra == "runtime-strict"
Requires-Dist: joblib==1.2.0; extra == "runtime-strict"
Requires-Dist: pyyaml<7,==6.0.2; (python_version >= "3.10" and python_version < "4.0") and extra == "runtime-strict"
Requires-Dist: pyyaml<7,==6.0.2; (python_version >= "3.9" and python_version < "3.10") and extra == "runtime-strict"
Requires-Dist: fiona==1.10.1; (python_version >= "3.11" and python_version < "4.0") and extra == "runtime-strict"
Requires-Dist: fiona==1.10.1; (python_version >= "3.9" and python_version < "3.11") and extra == "runtime-strict"
Requires-Dist: scikit-learn==1.6.0; (python_version >= "3.13" and python_version < "4.0") and extra == "runtime-strict"
Requires-Dist: scikit-learn==1.5.0; (python_version >= "3.12" and python_version < "3.13") and extra == "runtime-strict"
Requires-Dist: scikit-learn==1.5.0; (python_version >= "3.11" and python_version < "3.12") and extra == "runtime-strict"
Requires-Dist: scikit-learn==1.5.0; (python_version >= "3.10" and python_version < "3.11") and extra == "runtime-strict"
Requires-Dist: scikit-learn==1.5.0; (python_version >= "3.9" and python_version < "3.10") and extra == "runtime-strict"
Requires-Dist: scikit-image==0.24.0; (python_version >= "3.12" and python_version < "4.0") and extra == "runtime-strict"
Requires-Dist: scikit-image==0.20.0; (python_version >= "3.11" and python_version < "3.12") and extra == "runtime-strict"
Requires-Dist: scikit-image==0.19.3; (python_version >= "3.10" and python_version < "3.11") and extra == "runtime-strict"
Requires-Dist: scikit-image==0.18.1; (python_version >= "3.9" and python_version < "3.10") and extra == "runtime-strict"
Requires-Dist: pandas==2.2.3; (python_version >= "3.12" and python_version < "4.0") and extra == "runtime-strict"
Requires-Dist: pandas==2.2.3; (python_version >= "3.11" and python_version < "3.12") and extra == "runtime-strict"
Requires-Dist: pandas<2.3,==2.2.3; (python_version >= "3.9" and python_version < "3.11") and extra == "runtime-strict"
Requires-Dist: rasterio==1.4; (python_version >= "3.9" and python_version < "4.0") and extra == "runtime-strict"
Provides-Extra: tests-strict
Requires-Dist: xdoctest==1.0.2; extra == "tests-strict"
Requires-Dist: ubelt==1.2.1; extra == "tests-strict"
Requires-Dist: requests==2.25.1; extra == "tests-strict"
Requires-Dist: setuptools==76.0; python_version >= "3.12" and extra == "tests-strict"
Requires-Dist: pytest==6.2.5; python_version >= "3.10" and extra == "tests-strict"
Requires-Dist: pytest==6.2.5; (python_version >= "3.7" and python_version < "3.10") and extra == "tests-strict"
Requires-Dist: pytest-cov==3.0.0; python_version >= "3.6" and extra == "tests-strict"
Requires-Dist: pytest-timeout==1.4.2; extra == "tests-strict"
Requires-Dist: coverage==6.1.1; python_version >= "3.10" and extra == "tests-strict"
Requires-Dist: coverage==5.3.1; (python_version >= "3.9" and python_version < "3.10") and extra == "tests-strict"
Requires-Dist: coverage==6.1.1; (python_version >= "3.8" and python_version < "3.9") and extra == "tests-strict"
Requires-Dist: coverage==6.1.1; (python_version >= "3.7" and python_version < "3.8") and extra == "tests-strict"
Requires-Dist: coverage==6.1.1; (python_version >= "3.6" and python_version < "3.7") and extra == "tests-strict"
Provides-Extra: optional-strict
Requires-Dist: matplotlib==3.3.4; extra == "optional-strict"
Requires-Dist: Seaborn==0.9.0; extra == "optional-strict"
Requires-Dist: click==7.1.1; extra == "optional-strict"
Dynamic: author
Dynamic: author-email
Dynamic: classifier
Dynamic: description
Dynamic: description-content-type
Dynamic: home-page
Dynamic: license
Dynamic: license-file
Dynamic: provides-extra
Dynamic: requires-dist
Dynamic: requires-python
Dynamic: summary
